importio_client/__init__.py
importio_client/client.py
importio_client/exceptions.py
importio_client/utils.py
importio_client-0.2.4.dist-info/LICENSE
importio_client-0.2.4.dist-info/METADATA
importio_client-0.2.4.dist-info/WHEEL
importio_client-0.2.4.dist-info/top_level.txt
importio_client-0.2.4.dist-info/RECORD
