Metadata-Version: 2.1
Name: importio-client
Version: 0.2.4
Summary: A client library for interacting with the ImportIO API
Home-page: https://github.com/nickdkr/importio-client
Author: Nick Dekker
Author-email: 
Project-URL: Bug Tracker, https://github.com/nickdkr/importio-client/issues
Project-URL: Source Code, https://github.com/nickdkr/importio-client
Classifier: Development Status :: 3 - Alpha
Classifier: Intended Audience :: Developers
Classifier: License :: OSI Approved :: MIT License
Classifier: Operating System :: OS Independent
Classifier: Programming Language :: Python :: 3
Classifier: Programming Language :: Python :: 3.7
Classifier: Programming Language :: Python :: 3.8
Classifier: Programming Language :: Python :: 3.9
Classifier: Programming Language :: Python :: 3.10
Requires-Python: >=3.7
License-File: LICENSE
Requires-Dist: requests>=2.25.0
Provides-Extra: test
Requires-Dist: pytest>=6.0; extra == "test"
